{
	"IsEncrypted": false,
	"Values": {
		"TableStorageConnectionString": "DefaultEndpointsProtocol=https;AccountName=[[AccountName]];AccountKey=[[AccountKey]];BlobEndpoint=https://[[AccountName]].blob.core.windows.net/;TableEndpoint=https://[[AccountName]].table.core.windows.net/;QueueEndpoint=https://[[AccountName]].queue.core.windows.net/;FileEndpoint=https://[[AccountName]].file.core.windows.net/",
		"AzureWebJobsStorage": "UseDevelopmentStorage=true",
		"FUNCTIONS_WORKER_RUNTIME": "dotnet-isolated"
	},
	"Host": {
		"LocalHttpPort": 7071,
		"CORS": "*"
	}
}